.gitignore
AUTHORS.txt
BUILD.rst
CONTRIBUTING.rst
COPYRIGHT.txt
INSTALL.rst
LICENSE.txt
MANIFEST.in
README.rst
pom.xml
requirements.txt
robot.bmp
robot_postinstall.py
rundevel.py
setup.py
tasks.py
atest/README.rst
atest/genrunner.py
atest/run_atests.py
atest/resources/TestCheckerLibrary.py
atest/resources/TestHelper.py
atest/resources/atest_resource.robot
atest/resources/atest_variables.py
atest/resources/read_interpreter.py
atest/resources/rebot_resource.robot
atest/resources/unicode_vars.py
atest/robot/cli/console/colors_and_width.robot
atest/robot/cli/console/console_resource.robot
atest/robot/cli/console/console_type.robot
atest/robot/cli/console/encoding_from_env_vars.robot
atest/robot/cli/console/markers.robot
atest/robot/cli/console/monitor_options_are_deprecated.robot
atest/robot/cli/console/non_ascii.robot
atest/robot/cli/console/verbose_layout.robot
atest/robot/cli/console/expected_output/ExpectedOutputLibrary.py
atest/robot/cli/console/expected_output/dotted_fatal_error.txt
atest/robot/cli/console/expected_output/empty.txt
atest/robot/cli/console/expected_output/warnings_and_errors_stderr.txt
atest/robot/cli/console/expected_output/warnings_and_errors_stdout.txt
atest/robot/cli/console/expected_output/warnings_and_errors_stdout_dotted.txt
atest/robot/cli/dryrun/args.robot
atest/robot/cli/dryrun/dryrun.robot
atest/robot/cli/dryrun/executed_builtin_keywords.robot
atest/robot/cli/dryrun/java_arguments.robot
atest/robot/cli/dryrun/kwargs.robot
atest/robot/cli/dryrun/run_keyword_variants.robot
atest/robot/cli/dryrun/run_keyword_variants_in_suite_teardown.robot
atest/robot/cli/model_modifiers/ModelModifier.py
atest/robot/cli/model_modifiers/modifier_resource.robot
atest/robot/cli/model_modifiers/pre_rebot.robot
atest/robot/cli/model_modifiers/pre_rebot_when_running.robot
atest/robot/cli/model_modifiers/pre_run.robot
atest/robot/cli/rebot/REBOT_OPTIONS.robot
atest/robot/cli/rebot/__init__.robot
atest/robot/cli/rebot/argumentfile.robot
src/robotframework_python3.egg-info/PKG-INFO
src/robotframework_python3.egg-info/SOURCES.txt
src/robotframework_python3.egg-info/dependency_links.txt
src/robotframework_python3.egg-info/requires.txt
src/robotframework_python3.egg-info/top_level.txt
