Metadata-Version: 1.1
Name: robotframework-python3
Version: 2.9
Summary: Python 3 compatible generic test automation framework
Home-page: https://github.com/userzimmermann/robotframework/tree/python3
Author: Stefan Zimmermann
Author-email: zimmermann.code@gmail.com
License: Apache License 2.0
Download-URL: https://pypi.python.org/pypi/robotframework-python3
Keywords: robotframework testing testautomation acceptancetesting atdd bdd
Platform: any
Classifier: Development Status :: 5 - Production/Stable
Classifier: License :: OSI Approved :: Apache Software License
Classifier: Operating System :: OS Independent
Classifier: Programming Language :: Python
Classifier: Programming Language :: Python :: 2
Classifier: Programming Language :: Python :: 2.7
Classifier: Programming Language :: Python :: 3
Classifier: Programming Language :: Python :: 3.3
Classifier: Programming Language :: Python :: 3.4
Classifier: Topic :: Software Development :: Testing
